webAudit/__init__.py
webAudit/auditor.py
webAudit/cli.old.py
webAudit/cli.py
webAudit/crawler.py
webAudit/extractor.py
webAudit/pagespeed.py
webAudit/report.py
webAudit/seo.py
webAudit/utils.py
webAudit-0.1.3.dist-info/LICENSE
webAudit-0.1.3.dist-info/METADATA
webAudit-0.1.3.dist-info/WHEEL
webAudit-0.1.3.dist-info/entry_points.txt
webAudit-0.1.3.dist-info/top_level.txt
webAudit-0.1.3.dist-info/RECORD
