Metadata-Version: 2.1
Name: webAudit
Version: 0.1.3
Summary: Full website audit tool (broken links, SEO, PageSpeed)
Home-page: https://github.com/amjadsh345/website_audit
Author: Amjad khan
Author-email: info@shailatech.com
License: MIT
Classifier: Development Status :: 4 - Beta
Classifier: Programming Language :: Python :: 3
Classifier: License :: OSI Approved :: MIT License
Classifier: Operating System :: OS Independent
Classifier: Topic :: Internet :: WWW/HTTP
Classifier: Topic :: Software Development :: Libraries
Requires-Python: >=3.8
License-File: LICENSE
Requires-Dist: scrapy>=2.0
Requires-Dist: requests>=2.28
Requires-Dist: beautifulsoup4>=4.12
